zipline/__init__.py
zipline/__main__.py
zipline/_protocol.cp36-win32.pyd
zipline/_protocol.pxd
zipline/_protocol.pyx
zipline/_version.py
zipline/algorithm.py
zipline/algorithm_live.py
zipline/api.py
zipline/api.pyi
zipline/country.py
zipline/currency.py
zipline/dispatch.py
zipline/errors.py
zipline/extensions.py
zipline/protocol.py
zipline/test_algorithms.py
zipline/zipline_warnings.py
zipline/assets/__init__.py
zipline/assets/_assets.cp36-win32.pyd
zipline/assets/_assets.pxd
zipline/assets/_assets.pyx
zipline/assets/asset_db_migrations.py
zipline/assets/asset_db_schema.py
zipline/assets/asset_writer.py
zipline/assets/assets.py
zipline/assets/continuous_futures.cp36-win32.pyd
zipline/assets/continuous_futures.pyx
zipline/assets/exchange_info.py
zipline/assets/futures.py
zipline/assets/roll_finder.py
zipline/assets/synthetic.py
zipline/config/__init__.py
zipline/config/bundle.py
zipline/config/data_backend.py
zipline/data/__init__.py
zipline/data/_adjustments.cp36-win32.pyd
zipline/data/_adjustments.pyx
zipline/data/_equities.cp36-win32.pyd
zipline/data/_equities.pyx
zipline/data/_minute_bar_internal.cp36-win32.pyd
zipline/data/_minute_bar_internal.pyx
zipline/data/_resample.cp36-win32.pyd
zipline/data/_resample.pyx
zipline/data/adjustments.py
zipline/data/bar_reader.py
zipline/data/bcolz_daily_bars.py
zipline/data/benchmarks.py
zipline/data/continuous_future_reader.py
zipline/data/data_portal.py
zipline/data/data_portal_live.py
zipline/data/dispatch_bar_reader.py
zipline/data/hdf5_daily_bars.py
zipline/data/history_loader.py
zipline/data/in_memory_daily_bars.py
zipline/data/loader.py
zipline/data/minute_bars.py
zipline/data/psql_daily_bars.py
zipline/data/resample.py
zipline/data/session_bars.py
zipline/data/bundles/___polygon_api.py
zipline/data/bundles/__init__.py
zipline/data/bundles/alpaca_api.py
zipline/data/bundles/alpha_vantage_api.py
zipline/data/bundles/binance_api.py
zipline/data/bundles/binance_csv.py
zipline/data/bundles/common.py
zipline_trader-1.6.1.dist-info/LICENSE
zipline_trader-1.6.1.dist-info/METADATA
zipline_trader-1.6.1.dist-info/WHEEL
zipline_trader-1.6.1.dist-info/entry_points.txt
zipline_trader-1.6.1.dist-info/top_level.txt
zipline_trader-1.6.1.dist-info/RECORD
