Metadata-Version: 2.1
Name: zipline-trader
Version: 1.6.1
Summary: A backtester for financial algorithms.
Home-page: https://github.com/shlomikushchi/zipline-trader
Author: zipline-live community
Author-email: 
Maintainer: Shlomi Kushchi
License: Apache 2.0
Platform: UNKNOWN
Classifier: Development Status :: 4 - Beta
Classifier: License :: OSI Approved :: Apache Software License
Classifier: Natural Language :: English
Classifier: Programming Language :: Python
Classifier: Programming Language :: Python :: 2.7
Classifier: Programming Language :: Python :: 3.5
Classifier: Programming Language :: Python :: 3.6
Classifier: Operating System :: OS Independent
Classifier: Intended Audience :: Science/Research
Classifier: Topic :: Office/Business :: Financial
Classifier: Topic :: Scientific/Engineering :: Information Analysis
Classifier: Topic :: System :: Distributed Computing
Requires-Dist: pip (>=7.1.0)
Requires-Dist: setuptools (>18.0)
Requires-Dist: Logbook (>=0.12.5)
Requires-Dist: click (>=4.0.0)
Requires-Dist: six (>=1.10.0)
Requires-Dist: python-interface (>=1.5.3)
Requires-Dist: multipledispatch (>=0.6.0)
Requires-Dist: toolz (>=0.8.2)
Requires-Dist: numpy (<1.20)
Requires-Dist: pandas (<1.2.0)
Requires-Dist: pandas-datareader (>=0.9.0)
Requires-Dist: scipy (>=0.17.1)
Requires-Dist: patsy (>=0.4.0)
Requires-Dist: statsmodels (>=0.6.1)
Requires-Dist: empyrical (>=0.5.0)
Requires-Dist: pytz (>=2018.5)
Requires-Dist: iso3166 (>=0.9)
Requires-Dist: trading-calendars (>=1.6.1)
Requires-Dist: python-dateutil (>=2.4.2)
Requires-Dist: requests (>=2.9.1)
Requires-Dist: sqlalchemy (<1.4.0,>=1.0.8)
Requires-Dist: alembic (>=0.7.7)
Requires-Dist: tables (>=3.4.3)
Requires-Dist: lru-dict (>=1.1.4)
Requires-Dist: intervaltree (>=2.1.0)
Requires-Dist: bottleneck (>=1.0.0)
Requires-Dist: networkx (<2.0,>=1.9.1)
Requires-Dist: numexpr (==2.7.1)
Requires-Dist: iso4217 (>=1.6.20180829)
Requires-Dist: websockets (<9,>=7.0)
Requires-Dist: alpaca-trade-api (>=0.51.0)
Requires-Dist: PyYAML (==5.3.1)
Requires-Dist: IbPy2 (==0.8.0)
Requires-Dist: polling (==0.3.1)
Requires-Dist: h5py (==2.10.0)
Requires-Dist: html5lib (==1.1)
Requires-Dist: beautifulsoup4 (==4.9.3)
Requires-Dist: psycopg2 (==2.8.6)
Requires-Dist: alpha-vantage (==2.3.1)
Requires-Dist: ratelimit (==2.2.1)
Requires-Dist: bcolz (==1.2.1)
Provides-Extra: all
Requires-Dist: coverage (>=4.0.3) ; extra == 'all'
Requires-Dist: nose (>=1.3.7) ; extra == 'all'
Requires-Dist: parameterized (>=0.5.0) ; extra == 'all'
Requires-Dist: nose-ignore-docstring (>=0.2) ; extra == 'all'
Requires-Dist: nose-timer (>=0.5.0) ; extra == 'all'
Requires-Dist: mock (>=2.0.0) ; extra == 'all'
Requires-Dist: testfixtures (>=4.1.2) ; extra == 'all'
Requires-Dist: flake8 (>=3.3.0) ; extra == 'all'
Requires-Dist: matplotlib (>=1.5.3) ; extra == 'all'
Requires-Dist: responses (>=0.9.0) ; extra == 'all'
Requires-Dist: pip-tools (>=4.3.0) ; extra == 'all'
Requires-Dist: TA-Lib (>=0.4.9) ; extra == 'all'
Provides-Extra: dev
Requires-Dist: coverage (>=4.0.3) ; extra == 'dev'
Requires-Dist: nose (>=1.3.7) ; extra == 'dev'
Requires-Dist: parameterized (>=0.5.0) ; extra == 'dev'
Requires-Dist: nose-ignore-docstring (>=0.2) ; extra == 'dev'
Requires-Dist: nose-timer (>=0.5.0) ; extra == 'dev'
Requires-Dist: mock (>=2.0.0) ; extra == 'dev'
Requires-Dist: testfixtures (>=4.1.2) ; extra == 'dev'
Requires-Dist: flake8 (>=3.3.0) ; extra == 'dev'
Requires-Dist: matplotlib (>=1.5.3) ; extra == 'dev'
Requires-Dist: responses (>=0.9.0) ; extra == 'dev'
Requires-Dist: pip-tools (>=4.3.0) ; extra == 'dev'
Provides-Extra: talib
Requires-Dist: TA-Lib (>=0.4.9) ; extra == 'talib'
